py_sandbox/__init__.py
py_sandbox/cache.py
py_sandbox/help.py
py_sandbox/remote.py
py_sandbox/sandbox.py
py_sandbox/verify.py
py_sandbox-0.2.6.dist-info/METADATA
py_sandbox-0.2.6.dist-info/WHEEL
py_sandbox-0.2.6.dist-info/top_level.txt
py_sandbox-0.2.6.dist-info/RECORD
