Metadata-Version: 2.4
Name: py-sandbox
Version: 0.2.6
Summary: Secure sandbox for code execution with remote module loading
Author: Phanes
License-Expression: MIT
Project-URL: Homepage, https://github.com/phanes19122025-cmyk/phi-linux
Keywords: sandbox,security,remote,module,loader
Classifier: Programming Language :: Python :: 3
Classifier: Operating System :: OS Independent
Requires-Python: >=3.8
